printloghelp.py
printloghelp-0.1.1.dist-info/WHEEL
printloghelp-0.1.1.dist-info/METADATA
printloghelp-0.1.1.dist-info/RECORD
