Metadata-Version: 2.1
Name: printloghelp
Version: 0.1.1
Summary: ConsoleLog.info(text) or error(text) or warning(text)
Author: fab4key
Requires-Python: >=3.8,<4.0
Classifier: Programming Language :: Python :: 3
Classifier: Programming Language :: Python :: 3.8
Classifier: Programming Language :: Python :: 3.9
Requires-Dist: colorama (>=0.4.4,<0.5.0)
